openbb_ecb/__init__.py
openbb_ecb/models/__init__.py
openbb_ecb/models/balance_of_payments.py
openbb_ecb/models/currency_reference_rates.py
openbb_ecb/models/yield_curve.py
openbb_ecb/utils/__init__.py
openbb_ecb/utils/bps_series.py
openbb_ecb/utils/ecb_helpers.py
openbb_ecb/utils/yield_curve_series.py
openbb_ecb-1.5.1.dist-info/METADATA
openbb_ecb-1.5.1.dist-info/WHEEL
openbb_ecb-1.5.1.dist-info/entry_points.txt
openbb_ecb-1.5.1.dist-info/RECORD
